[{"BLCountry":"Afghanistan","DLCountry":"Switzerland","freq":1},{"BLCountry":"Afghanistan","DLCountry":"United States of America","freq":1},{"BLCountry":"Albania","DLCountry":"France","freq":1},{"BLCountry":"Albania","DLCountry":"Switzerland","freq":2},{"BLCountry":"Albania","DLCountry":"United States of America","freq":1},{"BLCountry":"Algeria","DLCountry":"France","freq":32},{"BLCountry":"Algeria","DLCountry":"Poland","freq":3},{"BLCountry":"American Samoa","DLCountry":"United States of America","freq":1},{"BLCountry":"Angola","DLCountry":"United Kingdom","freq":1},{"BLCountry":"Argentina","DLCountry":"France","freq":9},{"BLCountry":"Argentina","DLCountry":"Ireland","freq":1},{"BLCountry":"Argentina","DLCountry":"Switzerland","freq":3},{"BLCountry":"Argentina","DLCountry":"United Kingdom","freq":7},{"BLCountry":"Argentina","DLCountry":"United States of America","freq":14},{"BLCountry":"Armenia","DLCountry":"France","freq":2},{"BLCountry":"Armenia","DLCountry":"United States of America","freq":1},{"BLCountry":"Australia","DLCountry":"France","freq":21},{"BLCountry":"Australia","DLCountry":"Ireland","freq":1},{"BLCountry":"Australia","DLCountry":"Switzerland","freq":3},{"BLCountry":"Australia","DLCountry":"United Kingdom","freq":127},{"BLCountry":"Australia","DLCountry":"United States of America","freq":70},{"BLCountry":"Austria","DLCountry":"France","freq":20},{"BLCountry":"Austria","DLCountry":"Poland","freq":26},{"BLCountry":"Austria","DLCountry":"Switzerland","freq":39},{"BLCountry":"Austria","DLCountry":"Ukraine","freq":4},{"BLCountry":"Austria","DLCountry":"United Kingdom","freq":52},{"BLCountry":"Austria","DLCountry":"United States of America","freq":121},{"BLCountry":"Bangladesh","DLCountry":"France","freq":1},{"BLCountry":"Bangladesh","DLCountry":"Ireland","freq":1},{"BLCountry":"Bangladesh","DLCountry":"United Kingdom","freq":8},{"BLCountry":"Bangladesh","DLCountry":"United States of America","freq":3},{"BLCountry":"Barbados","DLCountry":"United Kingdom","freq":3},{"BLCountry":"Barbados","DLCountry":"United States of America","freq":4},{"BLCountry":"Belarus","DLCountry":"France","freq":9},{"BLCountry":"Belarus","DLCountry":"Poland","freq":17},{"BLCountry":"Belarus","DLCountry":"Ukraine","freq":6},{"BLCountry":"Belarus","DLCountry":"United Kingdom","freq":6},{"BLCountry":"Belarus","DLCountry":"United States of America","freq":38},{"BLCountry":"Belgium","DLCountry":"France","freq":65},{"BLCountry":"Belgium","DLCountry":"Poland","freq":2},{"BLCountry":"Belgium","DLCountry":"Switzerland","freq":9},{"BLCountry":"Belgium","DLCountry":"United Kingdom","freq":7},{"BLCountry":"Belgium","DLCountry":"United States of America","freq":16},{"BLCountry":"Belize","DLCountry":"United States of America","freq":1},{"BLCountry":"Benin","DLCountry":"France","freq":2},{"BLCountry":"Bermuda","DLCountry":"United Kingdom","freq":2},{"BLCountry":"Bosnia and Herzegovina","DLCountry":"Poland","freq":2},{"BLCountry":"Bosnia and Herzegovina","DLCountry":"Switzerland","freq":1},{"BLCountry":"Bosnia and Herzegovina","DLCountry":"United States of America","freq":2},{"BLCountry":"Brazil","DLCountry":"France","freq":9},{"BLCountry":"Brazil","DLCountry":"United Kingdom","freq":4},{"BLCountry":"Brazil","DLCountry":"United States of America","freq":3},{"BLCountry":"Bulgaria","DLCountry":"France","freq":7},{"BLCountry":"Bulgaria","DLCountry":"Poland","freq":1},{"BLCountry":"Bulgaria","DLCountry":"Switzerland","freq":3},{"BLCountry":"Bulgaria","DLCountry":"Ukraine","freq":1},{"BLCountry":"Bulgaria","DLCountry":"United Kingdom","freq":1},{"BLCountry":"Bulgaria","DLCountry":"United States of America","freq":2},{"BLCountry":"Cambodia","DLCountry":"United States of America","freq":1},{"BLCountry":"Canada","DLCountry":"France","freq":29},{"BLCountry":"Canada","DLCountry":"Ireland","freq":2},{"BLCountry":"Canada","DLCountry":"Poland","freq":2},{"BLCountry":"Canada","DLCountry":"Switzerland","freq":2},{"BLCountry":"Canada","DLCountry":"United Kingdom","freq":75},{"BLCountry":"Canada","DLCountry":"United States of America","freq":412},{"BLCountry":"Chile","DLCountry":"United Kingdom","freq":2},{"BLCountry":"Chile","DLCountry":"United States of America","freq":10},{"BLCountry":"China","DLCountry":"France","freq":5},{"BLCountry":"China","DLCountry":"United Kingdom","freq":12},{"BLCountry":"China","DLCountry":"United States of America","freq":34},{"BLCountry":"Colombia","DLCountry":"France","freq":2},{"BLCountry":"Colombia","DLCountry":"United Kingdom","freq":1},{"BLCountry":"Colombia","DLCountry":"United States of America","freq":3},{"BLCountry":"Croatia","DLCountry":"France","freq":1},{"BLCountry":"Croatia","DLCountry":"Poland","freq":3},{"BLCountry":"Croatia","DLCountry":"Switzerland","freq":3},{"BLCountry":"Croatia","DLCountry":"Ukraine","freq":1},{"BLCountry":"Croatia","DLCountry":"United Kingdom","freq":1},{"BLCountry":"Croatia","DLCountry":"United States of America","freq":12},{"BLCountry":"Cuba","DLCountry":"France","freq":3},{"BLCountry":"Cuba","DLCountry":"United Kingdom","freq":3},{"BLCountry":"Cuba","DLCountry":"United States of America","freq":24},{"BLCountry":"Cyprus No Mans Area","DLCountry":"United Kingdom","freq":2},{"BLCountry":"Czech Republic","DLCountry":"France","freq":7},{"BLCountry":"Czech Republic","DLCountry":"Poland","freq":31},{"BLCountry":"Czech Republic","DLCountry":"Switzerland","freq":16},{"BLCountry":"Czech Republic","DLCountry":"Ukraine","freq":2},{"BLCountry":"Czech Republic","DLCountry":"United Kingdom","freq":19},{"BLCountry":"Czech Republic","DLCountry":"United States of America","freq":53},{"BLCountry":"Denmark","DLCountry":"France","freq":2},{"BLCountry":"Denmark","DLCountry":"United Kingdom","freq":3},{"BLCountry":"Denmark","DLCountry":"United States of America","freq":21},{"BLCountry":"Dominica","DLCountry":"United Kingdom","freq":1},{"BLCountry":"Dominican Republic","DLCountry":"France","freq":2},{"BLCountry":"Dominican Republic","DLCountry":"United States of America","freq":2},{"BLCountry":"Ecuador","DLCountry":"United States of America","freq":2},{"BLCountry":"Egypt","DLCountry":"France","freq":11},{"BLCountry":"Egypt","DLCountry":"Switzerland","freq":4},{"BLCountry":"Egypt","DLCountry":"Ukraine","freq":1},{"BLCountry":"Egypt","DLCountry":"United Kingdom","freq":10},{"BLCountry":"Egypt","DLCountry":"United States of America","freq":10},{"BLCountry":"El Salvador","DLCountry":"France","freq":2},{"BLCountry":"Estonia","DLCountry":"France","freq":1},{"BLCountry":"Estonia","DLCountry":"Poland","freq":1},{"BLCountry":"Estonia","DLCountry":"United Kingdom","freq":5},{"BLCountry":"Estonia","DLCountry":"United States of America","freq":3},{"BLCountry":"Ethiopia","DLCountry":"United Kingdom","freq":1},{"BLCountry":"Ethiopia","DLCountry":"United States of America","freq":4},{"BLCountry":"Falkland Islands","DLCountry":"United Kingdom","freq":1},{"BLCountry":"Fiji","DLCountry":"United States of America","freq":1},{"BLCountry":"Finland","DLCountry":"France","freq":2},{"BLCountry":"Finland","DLCountry":"Switzerland","freq":3},{"BLCountry":"Finland","DLCountry":"United States of America","freq":13},{"BLCountry":"France","DLCountry":"Algeria","freq":12},{"BLCountry":"France","DLCountry":"Argentina","freq":8},{"BLCountry":"France","DLCountry":"Australia","freq":4},{"BLCountry":"France","DLCountry":"Austria","freq":3},{"BLCountry":"France","DLCountry":"Barbados","freq":1},{"BLCountry":"France","DLCountry":"Belarus","freq":1},{"BLCountry":"France","DLCountry":"Belgium","freq":18},{"BLCountry":"France","DLCountry":"Brazil","freq":5},{"BLCountry":"France","DLCountry":"Cambodia","freq":1},{"BLCountry":"France","DLCountry":"Canada","freq":8},{"BLCountry":"France","DLCountry":"China","freq":1},{"BLCountry":"France","DLCountry":"Cuba","freq":1},{"BLCountry":"France","DLCountry":"Czech Republic","freq":4},{"BLCountry":"France","DLCountry":"East Timor","freq":1},{"BLCountry":"France","DLCountry":"Egypt","freq":7},{"BLCountry":"France","DLCountry":"El Salvador","freq":1},{"BLCountry":"France","DLCountry":"France","freq":1816},{"BLCountry":"France","DLCountry":"Gabon","freq":1},{"BLCountry":"France","DLCountry":"Germany","freq":102},{"BLCountry":"France","DLCountry":"Greece","freq":1},{"BLCountry":"France","DLCountry":"Guernsey","freq":2},{"BLCountry":"France","DLCountry":"Hungary","freq":3},{"BLCountry":"France","DLCountry":"Iceland","freq":1},{"BLCountry":"France","DLCountry":"India","freq":4},{"BLCountry":"France","DLCountry":"Iran","freq":1},{"BLCountry":"France","DLCountry":"Ireland","freq":2},{"BLCountry":"France","DLCountry":"Italy","freq":19},{"BLCountry":"France","DLCountry":"Japan","freq":1},{"BLCountry":"France","DLCountry":"Laos","freq":3},{"BLCountry":"France","DLCountry":"Lesotho","freq":1},{"BLCountry":"France","DLCountry":"Lithuania","freq":1},{"BLCountry":"France","DLCountry":"Mali","freq":2},{"BLCountry":"France","DLCountry":"Mexico","freq":5},{"BLCountry":"France","DLCountry":"Morocco","freq":6},{"BLCountry":"France","DLCountry":"Netherlands","freq":2},{"BLCountry":"France","DLCountry":"Norway","freq":1},{"BLCountry":"France","DLCountry":"Papua New Guinea","freq":1},{"BLCountry":"France","DLCountry":"Peru","freq":1},{"BLCountry":"France","DLCountry":"Poland","freq":9},{"BLCountry":"France","DLCountry":"Republic of Serbia","freq":1},{"BLCountry":"France","DLCountry":"Romania","freq":1},{"BLCountry":"France","DLCountry":"Russia","freq":10},{"BLCountry":"France","DLCountry":"South Africa","freq":1},{"BLCountry":"France","DLCountry":"Spain","freq":12},{"BLCountry":"France","DLCountry":"Switzerland","freq":35},{"BLCountry":"France","DLCountry":"Thailand","freq":2},{"BLCountry":"France","DLCountry":"United Kingdom","freq":53},{"BLCountry":"France","DLCountry":"United States of America","freq":112},{"BLCountry":"France","DLCountry":"Vatican","freq":2},{"BLCountry":"France","DLCountry":"Venezuela","freq":1},{"BLCountry":"France","DLCountry":"Vietnam","freq":5},{"BLCountry":"French Polynesia","DLCountry":"United States of America","freq":2},{"BLCountry":"Gabon","DLCountry":"France","freq":1},{"BLCountry":"Gaza","DLCountry":"United Kingdom","freq":1},{"BLCountry":"Georgia","DLCountry":"France","freq":8},{"BLCountry":"Georgia","DLCountry":"Poland","freq":1},{"BLCountry":"Georgia","DLCountry":"Switzerland","freq":1},{"BLCountry":"Georgia","DLCountry":"Ukraine","freq":1},{"BLCountry":"Georgia","DLCountry":"United Kingdom","freq":1},{"BLCountry":"Georgia","DLCountry":"United States of America","freq":2},{"BLCountry":"Germany","DLCountry":"France","freq":141},{"BLCountry":"Germany","DLCountry":"Ireland","freq":3},{"BLCountry":"Germany","DLCountry":"Poland","freq":158},{"BLCountry":"Germany","DLCountry":"Switzerland","freq":144},{"BLCountry":"Germany","DLCountry":"Ukraine","freq":43},{"BLCountry":"Germany","DLCountry":"United Kingdom","freq":133},{"BLCountry":"Germany","DLCountry":"United States of America","freq":420},{"BLCountry":"Ghana","DLCountry":"France","freq":1},{"BLCountry":"Ghana","DLCountry":"United Kingdom","freq":3},{"BLCountry":"Greece","DLCountry":"France","freq":13},{"BLCountry":"Greece","DLCountry":"Switzerland","freq":2},{"BLCountry":"Greece","DLCountry":"United Kingdom","freq":2},{"BLCountry":"Greece","DLCountry":"United States of America","freq":13},{"BLCountry":"Guatemala","DLCountry":"France","freq":1},{"BLCountry":"Guatemala","DLCountry":"United States of America","freq":1},{"BLCountry":"Guernsey","DLCountry":"United Kingdom","freq":4},{"BLCountry":"Guinea","DLCountry":"United Kingdom","freq":1},{"BLCountry":"Guinea","DLCountry":"United States of America","freq":1},{"BLCountry":"Guyana","DLCountry":"France","freq":1},{"BLCountry":"Guyana","DLCountry":"United Kingdom","freq":2},{"BLCountry":"Guyana","DLCountry":"United States of America","freq":2},{"BLCountry":"Haiti","DLCountry":"France","freq":3},{"BLCountry":"Honduras","DLCountry":"France","freq":1},{"BLCountry":"Honduras","DLCountry":"United States of America","freq":3},{"BLCountry":"Hong Kong S.A.R.","DLCountry":"United Kingdom","freq":5},{"BLCountry":"Hong Kong S.A.R.","DLCountry":"United States of America","freq":5},{"BLCountry":"Hungary","DLCountry":"France","freq":21},{"BLCountry":"Hungary","DLCountry":"Ireland","freq":1},{"BLCountry":"Hungary","DLCountry":"Poland","freq":3},{"BLCountry":"Hungary","DLCountry":"Switzerland","freq":18},{"BLCountry":"Hungary","DLCountry":"Ukraine","freq":2},{"BLCountry":"Hungary","DLCountry":"United Kingdom","freq":26},{"BLCountry":"Hungary","DLCountry":"United States of America","freq":105},{"BLCountry":"Iceland","DLCountry":"United States of America","freq":1},{"BLCountry":"India","DLCountry":"France","freq":10},{"BLCountry":"India","DLCountry":"Ireland","freq":2},{"BLCountry":"India","DLCountry":"Switzerland","freq":2},{"BLCountry":"India","DLCountry":"United Kingdom","freq":163},{"BLCountry":"India","DLCountry":"United States of America","freq":38},{"BLCountry":"Indonesia","DLCountry":"France","freq":1},{"BLCountry":"Indonesia","DLCountry":"Switzerland","freq":2},{"BLCountry":"Indonesia","DLCountry":"United Kingdom","freq":1},{"BLCountry":"Indonesia","DLCountry":"United States of America","freq":4},{"BLCountry":"Iran","DLCountry":"France","freq":7},{"BLCountry":"Iran","DLCountry":"Switzerland","freq":4},{"BLCountry":"Iran","DLCountry":"United Kingdom","freq":3},{"BLCountry":"Iran","DLCountry":"United States of America","freq":10},{"BLCountry":"Iraq","DLCountry":"United Kingdom","freq":3},{"BLCountry":"Ireland","DLCountry":"Australia","freq":27},{"BLCountry":"Ireland","DLCountry":"Belgium","freq":3},{"BLCountry":"Ireland","DLCountry":"Canada","freq":13},{"BLCountry":"Ireland","DLCountry":"Egypt","freq":2},{"BLCountry":"Ireland","DLCountry":"France","freq":11},{"BLCountry":"Ireland","DLCountry":"Germany","freq":2},{"BLCountry":"Ireland","DLCountry":"India","freq":1},{"BLCountry":"Ireland","DLCountry":"Ireland","freq":171},{"BLCountry":"Ireland","DLCountry":"Isle of Man","freq":1},{"BLCountry":"Ireland","DLCountry":"Italy","freq":1},{"BLCountry":"Ireland","DLCountry":"Japan","freq":1},{"BLCountry":"Ireland","DLCountry":"Kenya","freq":1},{"BLCountry":"Ireland","DLCountry":"Libya","freq":1},{"BLCountry":"Ireland","DLCountry":"Netherlands","freq":1},{"BLCountry":"Ireland","DLCountry":"New Zealand","freq":7},{"BLCountry":"Ireland","DLCountry":"Nigeria","freq":1},{"BLCountry":"Ireland","DLCountry":"Russia","freq":1},{"BLCountry":"Ireland","DLCountry":"South Africa","freq":1},{"BLCountry":"Ireland","DLCountry":"Spain","freq":2},{"BLCountry":"Ireland","DLCountry":"Switzerland","freq":4},{"BLCountry":"Ireland","DLCountry":"Turkey","freq":2},{"BLCountry":"Ireland","DLCountry":"United Kingdom","freq":152},{"BLCountry":"Ireland","DLCountry":"United States of America","freq":142},{"BLCountry":"Ireland","DLCountry":"Zambia","freq":1},{"BLCountry":"Isle of Man","DLCountry":"United Kingdom","freq":1},{"BLCountry":"Isle of Man","DLCountry":"United States of America","freq":4},{"BLCountry":"Israel","DLCountry":"Switzerland","freq":1},{"BLCountry":"Israel","DLCountry":"United Kingdom","freq":2},{"BLCountry":"Israel","DLCountry":"United States of America","freq":5},{"BLCountry":"Italy","DLCountry":"France","freq":57},{"BLCountry":"Italy","DLCountry":"Poland","freq":5},{"BLCountry":"Italy","DLCountry":"Switzerland","freq":23},{"BLCountry":"Italy","DLCountry":"Ukraine","freq":2},{"BLCountry":"Italy","DLCountry":"United Kingdom","freq":26},{"BLCountry":"Italy","DLCountry":"United States of America","freq":144},{"BLCountry":"Ivory Coast","DLCountry":"United States of America","freq":1},{"BLCountry":"Jamaica","DLCountry":"Switzerland","freq":1},{"BLCountry":"Jamaica","DLCountry":"United Kingdom","freq":10},{"BLCountry":"Jamaica","DLCountry":"United States of America","freq":8},{"BLCountry":"Japan","DLCountry":"France","freq":2},{"BLCountry":"Japan","DLCountry":"Switzerland","freq":2},{"BLCountry":"Japan","DLCountry":"United Kingdom","freq":8},{"BLCountry":"Japan","DLCountry":"United States of America","freq":22},{"BLCountry":"Jersey","DLCountry":"United Kingdom","freq":1},{"BLCountry":"Kazakhstan","DLCountry":"France","freq":2},{"BLCountry":"Kenya","DLCountry":"United Kingdom","freq":2},{"BLCountry":"Korea No Mans Area","DLCountry":"France","freq":1},{"BLCountry":"Kosovo","DLCountry":"United States of America","freq":2},{"BLCountry":"Latvia","DLCountry":"France","freq":3},{"BLCountry":"Latvia","DLCountry":"Poland","freq":4},{"BLCountry":"Latvia","DLCountry":"United Kingdom","freq":2},{"BLCountry":"Latvia","DLCountry":"United States of America","freq":16},{"BLCountry":"Lebanon","DLCountry":"France","freq":1},{"BLCountry":"Lebanon","DLCountry":"United States of America","freq":1},{"BLCountry":"Lesotho","DLCountry":"United Kingdom","freq":1},{"BLCountry":"Libya","DLCountry":"Switzerland","freq":1},{"BLCountry":"Libya","DLCountry":"United Kingdom","freq":1},{"BLCountry":"Liechtenstein","DLCountry":"Switzerland","freq":1},{"BLCountry":"Lithuania","DLCountry":"France","freq":6},{"BLCountry":"Lithuania","DLCountry":"Ireland","freq":1},{"BLCountry":"Lithuania","DLCountry":"Poland","freq":18},{"BLCountry":"Lithuania","DLCountry":"Switzerland","freq":3},{"BLCountry":"Lithuania","DLCountry":"Ukraine","freq":2},{"BLCountry":"Lithuania","DLCountry":"United Kingdom","freq":6},{"BLCountry":"Lithuania","DLCountry":"United States of America","freq":20},{"BLCountry":"Luxembourg","DLCountry":"France","freq":5},{"BLCountry":"Luxembourg","DLCountry":"Switzerland","freq":1},{"BLCountry":"Luxembourg","DLCountry":"United States of America","freq":2},{"BLCountry":"Macedonia","DLCountry":"France","freq":1},{"BLCountry":"Madagascar","DLCountry":"France","freq":2},{"BLCountry":"Malaysia","DLCountry":"United Kingdom","freq":6},{"BLCountry":"Malaysia","DLCountry":"United States of America","freq":2},{"BLCountry":"Malta","DLCountry":"United Kingdom","freq":4},{"BLCountry":"Mauritius","DLCountry":"France","freq":1},{"BLCountry":"Mauritius","DLCountry":"United Kingdom","freq":1},{"BLCountry":"Mexico","DLCountry":"France","freq":5},{"BLCountry":"Mexico","DLCountry":"Switzerland","freq":1},{"BLCountry":"Mexico","DLCountry":"United Kingdom","freq":3},{"BLCountry":"Mexico","DLCountry":"United States of America","freq":62},{"BLCountry":"Moldova","DLCountry":"France","freq":2},{"BLCountry":"Moldova","DLCountry":"Ukraine","freq":1},{"BLCountry":"Moldova","DLCountry":"United States of America","freq":7},{"BLCountry":"Montenegro","DLCountry":"France","freq":6},{"BLCountry":"Montenegro","DLCountry":"Switzerland","freq":1},{"BLCountry":"Morocco","DLCountry":"France","freq":6},{"BLCountry":"Mozambique","DLCountry":"United Kingdom","freq":1},{"BLCountry":"Myanmar","DLCountry":"France","freq":2},{"BLCountry":"Myanmar","DLCountry":"United Kingdom","freq":3},{"BLCountry":"Myanmar","DLCountry":"United States of America","freq":3},{"BLCountry":"Namibia","DLCountry":"Ukraine","freq":1},{"BLCountry":"Nepal","DLCountry":"Switzerland","freq":1},{"BLCountry":"Netherlands","DLCountry":"France","freq":12},{"BLCountry":"Netherlands","DLCountry":"Poland","freq":69},{"BLCountry":"Netherlands","DLCountry":"Switzerland","freq":17},{"BLCountry":"Netherlands","DLCountry":"United Kingdom","freq":12},{"BLCountry":"Netherlands","DLCountry":"United States of America","freq":49},{"BLCountry":"New Caledonia","DLCountry":"France","freq":1},{"BLCountry":"New Caledonia","DLCountry":"United Kingdom","freq":1},{"BLCountry":"New Zealand","DLCountry":"France","freq":8},{"BLCountry":"New Zealand","DLCountry":"Poland","freq":1},{"BLCountry":"New Zealand","DLCountry":"United Kingdom","freq":38},{"BLCountry":"New Zealand","DLCountry":"United States of America","freq":16},{"BLCountry":"Nicaragua","DLCountry":"United States of America","freq":2},{"BLCountry":"Niger","DLCountry":"United Kingdom","freq":2},{"BLCountry":"Niger","DLCountry":"United States of America","freq":1},{"BLCountry":"Nigeria","DLCountry":"United Kingdom","freq":1},{"BLCountry":"Northern Cyprus","DLCountry":"France","freq":1},{"BLCountry":"Northern Cyprus","DLCountry":"United Kingdom","freq":1},{"BLCountry":"Northern Cyprus","DLCountry":"United States of America","freq":1},{"BLCountry":"Norway","DLCountry":"France","freq":3},{"BLCountry":"Norway","DLCountry":"Poland","freq":1},{"BLCountry":"Norway","DLCountry":"United Kingdom","freq":2},{"BLCountry":"Norway","DLCountry":"United States of America","freq":39},{"BLCountry":"Oman","DLCountry":"United Kingdom","freq":1},{"BLCountry":"Pakistan","DLCountry":"France","freq":3},{"BLCountry":"Pakistan","DLCountry":"United Kingdom","freq":13},{"BLCountry":"Pakistan","DLCountry":"United States of America","freq":3},{"BLCountry":"Panama","DLCountry":"United States of America","freq":3},{"BLCountry":"Peru","DLCountry":"France","freq":1},{"BLCountry":"Peru","DLCountry":"United Kingdom","freq":2},{"BLCountry":"Peru","DLCountry":"United States of America","freq":4},{"BLCountry":"Philippines","DLCountry":"United States of America","freq":11},{"BLCountry":"Pitcairn Islands","DLCountry":"United States of America","freq":1},{"BLCountry":"Poland","DLCountry":"Argentina","freq":3},{"BLCountry":"Poland","DLCountry":"Australia","freq":1},{"BLCountry":"Poland","DLCountry":"Austria","freq":36},{"BLCountry":"Poland","DLCountry":"Belarus","freq":3},{"BLCountry":"Poland","DLCountry":"Belgium","freq":4},{"BLCountry":"Poland","DLCountry":"Brazil","freq":1},{"BLCountry":"Poland","DLCountry":"Bulgaria","freq":2},{"BLCountry":"Poland","DLCountry":"Canada","freq":7},{"BLCountry":"Poland","DLCountry":"China","freq":2},{"BLCountry":"Poland","DLCountry":"Croatia","freq":3},{"BLCountry":"Poland","DLCountry":"Czech Republic","freq":18},{"BLCountry":"Poland","DLCountry":"Egypt","freq":1},{"BLCountry":"Poland","DLCountry":"France","freq":48},{"BLCountry":"Poland","DLCountry":"Georgia","freq":2},{"BLCountry":"Poland","DLCountry":"Germany","freq":636},{"BLCountry":"Poland","DLCountry":"Greece","freq":1},{"BLCountry":"Poland","DLCountry":"Hungary","freq":2},{"BLCountry":"Poland","DLCountry":"India","freq":1},{"BLCountry":"Poland","DLCountry":"Israel","freq":7},{"BLCountry":"Poland","DLCountry":"Italy","freq":16},{"BLCountry":"Poland","DLCountry":"Latvia","freq":3},{"BLCountry":"Poland","DLCountry":"Libya","freq":1},{"BLCountry":"Poland","DLCountry":"Lithuania","freq":2},{"BLCountry":"Poland","DLCountry":"Luxembourg","freq":1},{"BLCountry":"Poland","DLCountry":"Malta","freq":1},{"BLCountry":"Poland","DLCountry":"Mexico","freq":7},{"BLCountry":"Poland","DLCountry":"Netherlands","freq":10},{"BLCountry":"Poland","DLCountry":"Norway","freq":3},{"BLCountry":"Poland","DLCountry":"Pakistan","freq":2},{"BLCountry":"Poland","DLCountry":"Poland","freq":444},{"BLCountry":"Poland","DLCountry":"Republic of Serbia","freq":3},{"BLCountry":"Poland","DLCountry":"Romania","freq":2},{"BLCountry":"Poland","DLCountry":"Russia","freq":51},{"BLCountry":"Poland","DLCountry":"Saint Martin","freq":1},{"BLCountry":"Poland","DLCountry":"Slovakia","freq":3},{"BLCountry":"Poland","DLCountry":"South Africa","freq":2},{"BLCountry":"Poland","DLCountry":"South Korea","freq":1},{"BLCountry":"Poland","DLCountry":"Spain","freq":3},{"BLCountry":"Poland","DLCountry":"Sweden","freq":1},{"BLCountry":"Poland","DLCountry":"Switzerland","freq":36},{"BLCountry":"Poland","DLCountry":"Tunisia","freq":2},{"BLCountry":"Poland","DLCountry":"Turkmenistan","freq":1},{"BLCountry":"Poland","DLCountry":"Ukraine","freq":30},{"BLCountry":"Poland","DLCountry":"United Kingdom","freq":57},{"BLCountry":"Poland","DLCountry":"United States of America","freq":149},{"BLCountry":"Poland","DLCountry":"Uzbekistan","freq":1},{"BLCountry":"Poland","DLCountry":"West Bank","freq":18},{"BLCountry":"Portugal","DLCountry":"France","freq":2},{"BLCountry":"Portugal","DLCountry":"United Kingdom","freq":3},{"BLCountry":"Portugal","DLCountry":"United States of America","freq":1},{"BLCountry":"Puerto Rico","DLCountry":"Switzerland","freq":1},{"BLCountry":"Puerto Rico","DLCountry":"United States of America","freq":22},{"BLCountry":"Republic of Serbia","DLCountry":"France","freq":7},{"BLCountry":"Republic of Serbia","DLCountry":"Switzerland","freq":3},{"BLCountry":"Republic of Serbia","DLCountry":"United Kingdom","freq":3},{"BLCountry":"Republic of Serbia","DLCountry":"United States of America","freq":8},{"BLCountry":"Romania","DLCountry":"France","freq":24},{"BLCountry":"Romania","DLCountry":"Poland","freq":6},{"BLCountry":"Romania","DLCountry":"Switzerland","freq":4},{"BLCountry":"Romania","DLCountry":"Ukraine","freq":2},{"BLCountry":"Romania","DLCountry":"United Kingdom","freq":9},{"BLCountry":"Romania","DLCountry":"United States of America","freq":38},{"BLCountry":"Russia","DLCountry":"France","freq":116},{"BLCountry":"Russia","DLCountry":"Poland","freq":20},{"BLCountry":"Russia","DLCountry":"Switzerland","freq":23},{"BLCountry":"Russia","DLCountry":"Ukraine","freq":47},{"BLCountry":"Russia","DLCountry":"United Kingdom","freq":34},{"BLCountry":"Russia","DLCountry":"United States of America","freq":116},{"BLCountry":"Saint Kitts and Nevis","DLCountry":"United Kingdom","freq":1},{"BLCountry":"Saint Vincent and the Grenadines","DLCountry":"United Kingdom","freq":1},{"BLCountry":"Saint Vincent and the Grenadines","DLCountry":"United States of America","freq":2},{"BLCountry":"Saudi Arabia","DLCountry":"Switzerland","freq":1},{"BLCountry":"Saudi Arabia","DLCountry":"United States of America","freq":2},{"BLCountry":"Senegal","DLCountry":"France","freq":1},{"BLCountry":"Senegal","DLCountry":"United Kingdom","freq":1},{"BLCountry":"Sierra Leone","DLCountry":"United Kingdom","freq":2},{"BLCountry":"Singapore","DLCountry":"United Kingdom","freq":3},{"BLCountry":"Slovakia","DLCountry":"Poland","freq":2},{"BLCountry":"Slovakia","DLCountry":"Switzerland","freq":4},{"BLCountry":"Slovakia","DLCountry":"Ukraine","freq":1},{"BLCountry":"Slovakia","DLCountry":"United Kingdom","freq":2},{"BLCountry":"Slovakia","DLCountry":"United States of America","freq":17},{"BLCountry":"Slovenia","DLCountry":"France","freq":2},{"BLCountry":"Slovenia","DLCountry":"United States of America","freq":1},{"BLCountry":"South Africa","DLCountry":"France","freq":3},{"BLCountry":"South Africa","DLCountry":"Switzerland","freq":1},{"BLCountry":"South Africa","DLCountry":"United Kingdom","freq":59},{"BLCountry":"South Africa","DLCountry":"United States of America","freq":12},{"BLCountry":"South Korea","DLCountry":"United States of America","freq":3},{"BLCountry":"Spain","DLCountry":"France","freq":38},{"BLCountry":"Spain","DLCountry":"Switzerland","freq":3},{"BLCountry":"Spain","DLCountry":"United Kingdom","freq":9},{"BLCountry":"Spain","DLCountry":"United States of America","freq":28},{"BLCountry":"Sri Lanka","DLCountry":"France","freq":1},{"BLCountry":"Sri Lanka","DLCountry":"United Kingdom","freq":12},{"BLCountry":"Sri Lanka","DLCountry":"United States of America","freq":3},{"BLCountry":"Sweden","DLCountry":"France","freq":3},{"BLCountry":"Sweden","DLCountry":"United Kingdom","freq":2},{"BLCountry":"Sweden","DLCountry":"United States of America","freq":45},{"BLCountry":"Switzerland","DLCountry":"Algeria","freq":1},{"BLCountry":"Switzerland","DLCountry":"Argentina","freq":1},{"BLCountry":"Switzerland","DLCountry":"Australia","freq":1},{"BLCountry":"Switzerland","DLCountry":"Austria","freq":7},{"BLCountry":"Switzerland","DLCountry":"Brazil","freq":1},{"BLCountry":"Switzerland","DLCountry":"Bulgaria","freq":1},{"BLCountry":"Switzerland","DLCountry":"Canada","freq":2},{"BLCountry":"Switzerland","DLCountry":"Czech Republic","freq":2},{"BLCountry":"Switzerland","DLCountry":"Ethiopia","freq":1},{"BLCountry":"Switzerland","DLCountry":"France","freq":36},{"BLCountry":"Switzerland","DLCountry":"Germany","freq":46},{"BLCountry":"Switzerland","DLCountry":"Isle of Man","freq":1},{"BLCountry":"Switzerland","DLCountry":"Italy","freq":9},{"BLCountry":"Switzerland","DLCountry":"Liechtenstein","freq":1},{"BLCountry":"Switzerland","DLCountry":"Lithuania","freq":1},{"BLCountry":"Switzerland","DLCountry":"Luxembourg","freq":2},{"BLCountry":"Switzerland","DLCountry":"Mexico","freq":1},{"BLCountry":"Switzerland","DLCountry":"Morocco","freq":2},{"BLCountry":"Switzerland","DLCountry":"Netherlands","freq":1},{"BLCountry":"Switzerland","DLCountry":"New Zealand","freq":1},{"BLCountry":"Switzerland","DLCountry":"Norway","freq":2},{"BLCountry":"Switzerland","DLCountry":"Peru","freq":1},{"BLCountry":"Switzerland","DLCountry":"Poland","freq":2},{"BLCountry":"Switzerland","DLCountry":"Russia","freq":3},{"BLCountry":"Switzerland","DLCountry":"Spain","freq":2},{"BLCountry":"Switzerland","DLCountry":"Switzerland","freq":222},{"BLCountry":"Switzerland","DLCountry":"Uganda","freq":1},{"BLCountry":"Switzerland","DLCountry":"United Kingdom","freq":6},{"BLCountry":"Switzerland","DLCountry":"United States of America","freq":39},{"BLCountry":"Switzerland","DLCountry":"West Bank","freq":1},{"BLCountry":"Syria","DLCountry":"France","freq":3},{"BLCountry":"Syria","DLCountry":"United States of America","freq":1},{"BLCountry":"Taiwan","DLCountry":"France","freq":1},{"BLCountry":"Thailand","DLCountry":"France","freq":1},{"BLCountry":"Thailand","DLCountry":"United Kingdom","freq":3},{"BLCountry":"Thailand","DLCountry":"United States of America","freq":1},{"BLCountry":"The Bahamas","DLCountry":"United Kingdom","freq":1},{"BLCountry":"The Bahamas","DLCountry":"United States of America","freq":2},{"BLCountry":"Togo","DLCountry":"France","freq":1},{"BLCountry":"Trinidad and Tobago","DLCountry":"United Kingdom","freq":4},{"BLCountry":"Trinidad and Tobago","DLCountry":"United States of America","freq":1},{"BLCountry":"Tunisia","DLCountry":"France","freq":1},{"BLCountry":"Turkey","DLCountry":"France","freq":31},{"BLCountry":"Turkey","DLCountry":"Switzerland","freq":1},{"BLCountry":"Turkey","DLCountry":"United Kingdom","freq":6},{"BLCountry":"Turkey","DLCountry":"United States of America","freq":22},{"BLCountry":"Uganda","DLCountry":"United Kingdom","freq":1},{"BLCountry":"Ukraine","DLCountry":"Argentina","freq":5},{"BLCountry":"Ukraine","DLCountry":"Australia","freq":4},{"BLCountry":"Ukraine","DLCountry":"Austria","freq":20},{"BLCountry":"Ukraine","DLCountry":"Belarus","freq":4},{"BLCountry":"Ukraine","DLCountry":"Belgium","freq":1},{"BLCountry":"Ukraine","DLCountry":"Brazil","freq":3},{"BLCountry":"Ukraine","DLCountry":"Bulgaria","freq":4},{"BLCountry":"Ukraine","DLCountry":"Canada","freq":12},{"BLCountry":"Ukraine","DLCountry":"China","freq":3},{"BLCountry":"Ukraine","DLCountry":"Croatia","freq":1},{"BLCountry":"Ukraine","DLCountry":"Czech Republic","freq":11},{"BLCountry":"Ukraine","DLCountry":"Estonia","freq":1},{"BLCountry":"Ukraine","DLCountry":"Finland","freq":1},{"BLCountry":"Ukraine","DLCountry":"France","freq":39},{"BLCountry":"Ukraine","DLCountry":"Georgia","freq":2},{"BLCountry":"Ukraine","DLCountry":"Germany","freq":33},{"BLCountry":"Ukraine","DLCountry":"Hungary","freq":5},{"BLCountry":"Ukraine","DLCountry":"Ireland","freq":1},{"BLCountry":"Ukraine","DLCountry":"Israel","freq":13},{"BLCountry":"Ukraine","DLCountry":"Italy","freq":12},{"BLCountry":"Ukraine","DLCountry":"Kazakhstan","freq":1},{"BLCountry":"Ukraine","DLCountry":"Latvia","freq":1},{"BLCountry":"Ukraine","DLCountry":"Lithuania","freq":1},{"BLCountry":"Ukraine","DLCountry":"Luxembourg","freq":1},{"BLCountry":"Ukraine","DLCountry":"Mexico","freq":3},{"BLCountry":"Ukraine","DLCountry":"Morocco","freq":1},{"BLCountry":"Ukraine","DLCountry":"Netherlands","freq":4},{"BLCountry":"Ukraine","DLCountry":"Philippines","freq":1},{"BLCountry":"Ukraine","DLCountry":"Poland","freq":63},{"BLCountry":"Ukraine","DLCountry":"Puerto Rico","freq":1},{"BLCountry":"Ukraine","DLCountry":"Romania","freq":4},{"BLCountry":"Ukraine","DLCountry":"Russia","freq":195},{"BLCountry":"Ukraine","DLCountry":"South Africa","freq":1},{"BLCountry":"Ukraine","DLCountry":"Spain","freq":2},{"BLCountry":"Ukraine","DLCountry":"Sweden","freq":1},{"BLCountry":"Ukraine","DLCountry":"Switzerland","freq":7},{"BLCountry":"Ukraine","DLCountry":"Ukraine","freq":63},{"BLCountry":"Ukraine","DLCountry":"United Kingdom","freq":38},{"BLCountry":"Ukraine","DLCountry":"United States of America","freq":116},{"BLCountry":"Ukraine","DLCountry":"West Bank","freq":19},{"BLCountry":"United Kingdom","DLCountry":"Algeria","freq":3},{"BLCountry":"United Kingdom","DLCountry":"Argentina","freq":6},{"BLCountry":"United Kingdom","DLCountry":"Australia","freq":267},{"BLCountry":"United Kingdom","DLCountry":"Austria","freq":5},{"BLCountry":"United Kingdom","DLCountry":"Barbados","freq":2},{"BLCountry":"United Kingdom","DLCountry":"Belgium","freq":69},{"BLCountry":"United Kingdom","DLCountry":"Bermuda","freq":2},{"BLCountry":"United Kingdom","DLCountry":"Brazil","freq":2},{"BLCountry":"United Kingdom","DLCountry":"Cambodia","freq":2},{"BLCountry":"United Kingdom","DLCountry":"Canada","freq":198},{"BLCountry":"United Kingdom","DLCountry":"China","freq":15},{"BLCountry":"United Kingdom","DLCountry":"Croatia","freq":2},{"BLCountry":"United Kingdom","DLCountry":"Czech Republic","freq":1},{"BLCountry":"United Kingdom","DLCountry":"Denmark","freq":1},{"BLCountry":"United Kingdom","DLCountry":"Dominican Republic","freq":1},{"BLCountry":"United Kingdom","DLCountry":"Egypt","freq":12},{"BLCountry":"United Kingdom","DLCountry":"Falkland Islands","freq":2},{"BLCountry":"United Kingdom","DLCountry":"France","freq":245},{"BLCountry":"United Kingdom","DLCountry":"Germany","freq":55},{"BLCountry":"United Kingdom","DLCountry":"Greece","freq":6},{"BLCountry":"United Kingdom","DLCountry":"Guernsey","freq":4},{"BLCountry":"United Kingdom","DLCountry":"Hong Kong S.A.R.","freq":2},{"BLCountry":"United Kingdom","DLCountry":"Hungary","freq":2},{"BLCountry":"United Kingdom","DLCountry":"Iceland","freq":1},{"BLCountry":"United Kingdom","DLCountry":"India","freq":26},{"BLCountry":"United Kingdom","DLCountry":"Indonesia","freq":1},{"BLCountry":"United Kingdom","DLCountry":"Iraq","freq":6},{"BLCountry":"United Kingdom","DLCountry":"Ireland","freq":50},{"BLCountry":"United Kingdom","DLCountry":"Isle of Man","freq":9},{"BLCountry":"United Kingdom","DLCountry":"Israel","freq":6},{"BLCountry":"United Kingdom","DLCountry":"Italy","freq":52},{"BLCountry":"United Kingdom","DLCountry":"Jamaica","freq":4},{"BLCountry":"United Kingdom","DLCountry":"Japan","freq":7},{"BLCountry":"United Kingdom","DLCountry":"Jersey","freq":1},{"BLCountry":"United Kingdom","DLCountry":"Jordan","freq":1},{"BLCountry":"United Kingdom","DLCountry":"Kenya","freq":6},{"BLCountry":"United Kingdom","DLCountry":"Latvia","freq":1},{"BLCountry":"United Kingdom","DLCountry":"Lebanon","freq":1},{"BLCountry":"United Kingdom","DLCountry":"Libya","freq":3},{"BLCountry":"United Kingdom","DLCountry":"Malaysia","freq":4},{"BLCountry":"United Kingdom","DLCountry":"Malta","freq":4},{"BLCountry":"United Kingdom","DLCountry":"Mexico","freq":4},{"BLCountry":"United Kingdom","DLCountry":"Mongolia","freq":1},{"BLCountry":"United Kingdom","DLCountry":"Morocco","freq":4},{"BLCountry":"United Kingdom","DLCountry":"Mozambique","freq":1},{"BLCountry":"United Kingdom","DLCountry":"Myanmar","freq":9},{"BLCountry":"United Kingdom","DLCountry":"Namibia","freq":1},{"BLCountry":"United Kingdom","DLCountry":"Nepal","freq":1},{"BLCountry":"United Kingdom","DLCountry":"Netherlands","freq":17},{"BLCountry":"United Kingdom","DLCountry":"New Zealand","freq":65},{"BLCountry":"United Kingdom","DLCountry":"Niger","freq":1},{"BLCountry":"United Kingdom","DLCountry":"Nigeria","freq":1},{"BLCountry":"United Kingdom","DLCountry":"North Korea","freq":1},{"BLCountry":"United Kingdom","DLCountry":"Northern Cyprus","freq":3},{"BLCountry":"United Kingdom","DLCountry":"Norway","freq":4},{"BLCountry":"United Kingdom","DLCountry":"Pakistan","freq":6},{"BLCountry":"United Kingdom","DLCountry":"Panama","freq":1},{"BLCountry":"United Kingdom","DLCountry":"Papua New Guinea","freq":1},{"BLCountry":"United Kingdom","DLCountry":"Peru","freq":2},{"BLCountry":"United Kingdom","DLCountry":"Poland","freq":3},{"BLCountry":"United Kingdom","DLCountry":"Portugal","freq":2},{"BLCountry":"United Kingdom","DLCountry":"Republic of Serbia","freq":1},{"BLCountry":"United Kingdom","DLCountry":"Romania","freq":2},{"BLCountry":"United Kingdom","DLCountry":"Russia","freq":3},{"BLCountry":"United Kingdom","DLCountry":"Saint Kitts and Nevis","freq":1},{"BLCountry":"United Kingdom","DLCountry":"Singapore","freq":2},{"BLCountry":"United Kingdom","DLCountry":"Somalia","freq":2},{"BLCountry":"United Kingdom","DLCountry":"South Africa","freq":73},{"BLCountry":"United Kingdom","DLCountry":"South Korea","freq":1},{"BLCountry":"United Kingdom","DLCountry":"Spain","freq":31},{"BLCountry":"United Kingdom","DLCountry":"Suriname","freq":1},{"BLCountry":"United Kingdom","DLCountry":"Switzerland","freq":26},{"BLCountry":"United Kingdom","DLCountry":"Taiwan","freq":1},{"BLCountry":"United Kingdom","DLCountry":"Thailand","freq":1},{"BLCountry":"United Kingdom","DLCountry":"The Bahamas","freq":3},{"BLCountry":"United Kingdom","DLCountry":"Tunisia","freq":2},{"BLCountry":"United Kingdom","DLCountry":"Turkey","freq":8},{"BLCountry":"United Kingdom","DLCountry":"Tuvalu","freq":1},{"BLCountry":"United Kingdom","DLCountry":"United Kingdom","freq":6784},{"BLCountry":"United Kingdom","DLCountry":"United States of America","freq":816},{"BLCountry":"United Kingdom","DLCountry":"Venezuela","freq":1},{"BLCountry":"United Kingdom","DLCountry":"West Bank","freq":6},{"BLCountry":"United Kingdom","DLCountry":"Zimbabwe","freq":12},{"BLCountry":"United Republic of Tanzania","DLCountry":"Poland","freq":1},{"BLCountry":"United Republic of Tanzania","DLCountry":"United Kingdom","freq":2},{"BLCountry":"United States of America","DLCountry":"Afghanistan","freq":2},{"BLCountry":"United States of America","DLCountry":"Algeria","freq":2},{"BLCountry":"United States of America","DLCountry":"American Samoa","freq":1},{"BLCountry":"United States of America","DLCountry":"Anguilla","freq":1},{"BLCountry":"United States of America","DLCountry":"Australia","freq":12},{"BLCountry":"United States of America","DLCountry":"Austria","freq":11},{"BLCountry":"United States of America","DLCountry":"Barbados","freq":2},{"BLCountry":"United States of America","DLCountry":"Belgium","freq":10},{"BLCountry":"United States of America","DLCountry":"Bermuda","freq":2},{"BLCountry":"United States of America","DLCountry":"Bolivia","freq":2},{"BLCountry":"United States of America","DLCountry":"Brazil","freq":3},{"BLCountry":"United States of America","DLCountry":"Cambodia","freq":1},{"BLCountry":"United States of America","DLCountry":"Canada","freq":127},{"BLCountry":"United States of America","DLCountry":"Chad","freq":1},{"BLCountry":"United States of America","DLCountry":"China","freq":18},{"BLCountry":"United States of America","DLCountry":"Colombia","freq":2},{"BLCountry":"United States of America","DLCountry":"Costa Rica","freq":3},{"BLCountry":"United States of America","DLCountry":"Croatia","freq":1},{"BLCountry":"United States of America","DLCountry":"Cuba","freq":2},{"BLCountry":"United States of America","DLCountry":"Czech Republic","freq":1},{"BLCountry":"United States of America","DLCountry":"Democratic Republic of the Congo","freq":1},{"BLCountry":"United States of America","DLCountry":"Denmark","freq":2},{"BLCountry":"United States of America","DLCountry":"Dominican Republic","freq":1},{"BLCountry":"United States of America","DLCountry":"Ecuador","freq":4},{"BLCountry":"United States of America","DLCountry":"Egypt","freq":3},{"BLCountry":"United States of America","DLCountry":"El Salvador","freq":2},{"BLCountry":"United States of America","DLCountry":"Eritrea","freq":1},{"BLCountry":"United States of America","DLCountry":"Ethiopia","freq":1},{"BLCountry":"United States of America","DLCountry":"Finland","freq":2},{"BLCountry":"United States of America","DLCountry":"France","freq":151},{"BLCountry":"United States of America","DLCountry":"French Polynesia","freq":1},{"BLCountry":"United States of America","DLCountry":"Germany","freq":59},{"BLCountry":"United States of America","DLCountry":"Ghana","freq":1},{"BLCountry":"United States of America","DLCountry":"Greece","freq":4},{"BLCountry":"United States of America","DLCountry":"Grenada","freq":1},{"BLCountry":"United States of America","DLCountry":"Guatemala","freq":1},{"BLCountry":"United States of America","DLCountry":"Guyana","freq":3},{"BLCountry":"United States of America","DLCountry":"Haiti","freq":2},{"BLCountry":"United States of America","DLCountry":"Hong Kong S.A.R.","freq":7},{"BLCountry":"United States of America","DLCountry":"Iceland","freq":1},{"BLCountry":"United States of America","DLCountry":"India","freq":7},{"BLCountry":"United States of America","DLCountry":"Indonesia","freq":2},{"BLCountry":"United States of America","DLCountry":"Iran","freq":2},{"BLCountry":"United States of America","DLCountry":"Ireland","freq":4},{"BLCountry":"United States of America","DLCountry":"Isle of Man","freq":1},{"BLCountry":"United States of America","DLCountry":"Israel","freq":5},{"BLCountry":"United States of America","DLCountry":"Italy","freq":56},{"BLCountry":"United States of America","DLCountry":"Jamaica","freq":2},{"BLCountry":"United States of America","DLCountry":"Japan","freq":36},{"BLCountry":"United States of America","DLCountry":"Korea No Mans Area","freq":32},{"BLCountry":"United States of America","DLCountry":"Laos","freq":13},{"BLCountry":"United States of America","DLCountry":"Lebanon","freq":4},{"BLCountry":"United States of America","DLCountry":"Lesotho","freq":1},{"BLCountry":"United States of America","DLCountry":"Liberia","freq":2},{"BLCountry":"United States of America","DLCountry":"Libya","freq":1},{"BLCountry":"United States of America","DLCountry":"Madagascar","freq":1},{"BLCountry":"United States of America","DLCountry":"Mauritius","freq":1},{"BLCountry":"United States of America","DLCountry":"Mexico","freq":62},{"BLCountry":"United States of America","DLCountry":"Morocco","freq":3},{"BLCountry":"United States of America","DLCountry":"Myanmar","freq":1},{"BLCountry":"United States of America","DLCountry":"Nepal","freq":2},{"BLCountry":"United States of America","DLCountry":"Netherlands","freq":11},{"BLCountry":"United States of America","DLCountry":"New Caledonia","freq":1},{"BLCountry":"United States of America","DLCountry":"New Zealand","freq":3},{"BLCountry":"United States of America","DLCountry":"Nicaragua","freq":1},{"BLCountry":"United States of America","DLCountry":"Nigeria","freq":1},{"BLCountry":"United States of America","DLCountry":"North Korea","freq":8},{"BLCountry":"United States of America","DLCountry":"Northern Mariana Islands","freq":8},{"BLCountry":"United States of America","DLCountry":"Norway","freq":4},{"BLCountry":"United States of America","DLCountry":"Pakistan","freq":1},{"BLCountry":"United States of America","DLCountry":"Palau","freq":1},{"BLCountry":"United States of America","DLCountry":"Panama","freq":5},{"BLCountry":"United States of America","DLCountry":"Papua New Guinea","freq":12},{"BLCountry":"United States of America","DLCountry":"Peru","freq":2},{"BLCountry":"United States of America","DLCountry":"Philippines","freq":26},{"BLCountry":"United States of America","DLCountry":"Poland","freq":4},{"BLCountry":"United States of America","DLCountry":"Portugal","freq":2},{"BLCountry":"United States of America","DLCountry":"Puerto Rico","freq":8},{"BLCountry":"United States of America","DLCountry":"Romania","freq":4},{"BLCountry":"United States of America","DLCountry":"Russia","freq":7},{"BLCountry":"United States of America","DLCountry":"Rwanda","freq":1},{"BLCountry":"United States of America","DLCountry":"San Marino","freq":1},{"BLCountry":"United States of America","DLCountry":"Sierra Leone","freq":1},{"BLCountry":"United States of America","DLCountry":"Slovakia","freq":1},{"BLCountry":"United States of America","DLCountry":"Solomon Islands","freq":35},{"BLCountry":"United States of America","DLCountry":"Somalia","freq":7},{"BLCountry":"United States of America","DLCountry":"South Africa","freq":2},{"BLCountry":"United States of America","DLCountry":"South Korea","freq":5},{"BLCountry":"United States of America","DLCountry":"Spain","freq":12},{"BLCountry":"United States of America","DLCountry":"Sri Lanka","freq":1},{"BLCountry":"United States of America","DLCountry":"Sweden","freq":7},{"BLCountry":"United States of America","DLCountry":"Switzerland","freq":20},{"BLCountry":"United States of America","DLCountry":"Taiwan","freq":1},{"BLCountry":"United States of America","DLCountry":"Thailand","freq":7},{"BLCountry":"United States of America","DLCountry":"The Bahamas","freq":4},{"BLCountry":"United States of America","DLCountry":"Tunisia","freq":1},{"BLCountry":"United States of America","DLCountry":"Turkey","freq":1},{"BLCountry":"United States of America","DLCountry":"Ukraine","freq":1},{"BLCountry":"United States of America","DLCountry":"United Kingdom","freq":166},{"BLCountry":"United States of America","DLCountry":"United States of America","freq":23161},{"BLCountry":"United States of America","DLCountry":"United States Virgin Islands","freq":4},{"BLCountry":"United States of America","DLCountry":"Venezuela","freq":1},{"BLCountry":"United States of America","DLCountry":"Vietnam","freq":47},{"BLCountry":"United States of America","DLCountry":"West Bank","freq":7},{"BLCountry":"United States of America","DLCountry":"Zimbabwe","freq":1},{"BLCountry":"United States Virgin Islands","DLCountry":"France","freq":1},{"BLCountry":"United States Virgin Islands","DLCountry":"United States of America","freq":3},{"BLCountry":"Uruguay","DLCountry":"France","freq":2},{"BLCountry":"Uruguay","DLCountry":"Switzerland","freq":1},{"BLCountry":"Uruguay","DLCountry":"United States of America","freq":4},{"BLCountry":"Uzbekistan","DLCountry":"France","freq":1},{"BLCountry":"Uzbekistan","DLCountry":"Poland","freq":1},{"BLCountry":"Uzbekistan","DLCountry":"Ukraine","freq":2},{"BLCountry":"Uzbekistan","DLCountry":"United States of America","freq":1},{"BLCountry":"Vatican","DLCountry":"United Kingdom","freq":1},{"BLCountry":"Venezuela","DLCountry":"France","freq":4},{"BLCountry":"Venezuela","DLCountry":"Switzerland","freq":1},{"BLCountry":"Venezuela","DLCountry":"United States of America","freq":3},{"BLCountry":"Vietnam","DLCountry":"France","freq":8},{"BLCountry":"Vietnam","DLCountry":"United States of America","freq":1},{"BLCountry":"West Bank","DLCountry":"Ireland","freq":1},{"BLCountry":"West Bank","DLCountry":"United Kingdom","freq":1},{"BLCountry":"West Bank","DLCountry":"United States of America","freq":2},{"BLCountry":"Yemen","DLCountry":"United Kingdom","freq":1},{"BLCountry":"Zambia","DLCountry":"United States of America","freq":1},{"BLCountry":"Zimbabwe","DLCountry":"United Kingdom","freq":1}]
